pythinq2/__init__.py
pythinq2/api.py
pythinq2/auth.py
pythinq2/cli.py
pythinq2/constants.py
pythinq2/gateway.py
pythinq2/utils.py
pythinq2-0.2.0.dist-info/LICENSE
pythinq2-0.2.0.dist-info/METADATA
pythinq2-0.2.0.dist-info/WHEEL
pythinq2-0.2.0.dist-info/entry_points.txt
pythinq2-0.2.0.dist-info/top_level.txt
pythinq2-0.2.0.dist-info/RECORD
