Metadata-Version: 2.1
Name: pythinq2
Version: 0.2.0
Summary: A package to interact with LG smart devices.
Author-email: Jeffrey Muller <jeffrey.muller92@gmail.com>
License: MIT
Classifier: Programming Language :: Python :: 3
Requires-Python: >=3.10
License-File: LICENSE
Requires-Dist: docopt <1.0.0,>=0.6.2
Requires-Dist: requests <3.0.0,>=2.31.0
Requires-Dist: tabulate <1.0.0,>=0.9.0
Provides-Extra: dev
Requires-Dist: black ; extra == 'dev'
Requires-Dist: ruff ; extra == 'dev'
